iter_pipes/__init__.py
iter_pipes/functional.py
iter_pipes/main.py
iter_pipes-0.1.7.dist-info/LICENSE
iter_pipes-0.1.7.dist-info/METADATA
iter_pipes-0.1.7.dist-info/WHEEL
iter_pipes-0.1.7.dist-info/RECORD
