Metadata-Version: 2.1
Name: iter-pipes
Version: 0.1.7
Summary: Functional pythonic pipelines for iterables.
Home-page: https://github.com/brightnetwork/iter-pipes
License: MIT
Keywords: iterable,pipes,collection
Author: brightnetwork
Author-email: dev@brightnetwork.co.uk
Requires-Python: >=3.10,<4.0
Classifier: License :: OSI Approved :: MIT License
Classifier: Programming Language :: Python :: 3
Classifier: Programming Language :: Python :: 3.10
Classifier: Programming Language :: Python :: 3.11
Classifier: Programming Language :: Python :: 3.12
Project-URL: Documentation, https://github.com/brightnetwork/iter-pipes
Project-URL: Repository, https://github.com/brightnetwork/iter-pipes
